pibrary/__init__.py
pibrary/file.py
pibrary/logger.py
pibrary/loguru.py
pibrary/string.py
pibrary/visualization.py
pibrary/wandb.py
pibrary-0.4.1.dist-info/LICENSE
pibrary-0.4.1.dist-info/METADATA
pibrary-0.4.1.dist-info/WHEEL
pibrary-0.4.1.dist-info/RECORD
