Metadata-Version: 2.3
Name: pibrary
Version: 0.4.1
Summary: A package of reusable code for ML projects
License: MIT
Author: Prakash Chaudhary
Author-email: connectwithprakash@gmail.com
Requires-Python: >=3.9
Classifier: License :: OSI Approved :: MIT License
Classifier: Programming Language :: Python :: 3
Classifier: Programming Language :: Python :: 3.9
Classifier: Programming Language :: Python :: 3.10
Classifier: Programming Language :: Python :: 3.11
Classifier: Programming Language :: Python :: 3.12
Classifier: Programming Language :: Python :: 3.13
Requires-Dist: autoapi (>=2.0.1)
Requires-Dist: joblib (>=1.2.0)
Requires-Dist: loguru (>=0.7.0)
Requires-Dist: pandas (>=2.2.2)
Requires-Dist: sphinx-autoapi (>=3.2.1)
Requires-Dist: wandb (>=0.16.3)
